{"resourceType":"Bundle","type":"searchset","entry":[{"resource":{"resourceType":"Parameters","id":"ImmDS-2013-0692","parameter":[{"name":"assessentDate","valueDate":"2020-06-29"},{"name":"patient","resource":{"resourceType":"Patient","id":"2013-0692","name":[{"text":"# 5 Pediarix at 4 yrs -4 days\nEvaluation_Test_Type: Age: At Absolute Minimum\nGeneral_Description: This test case describes when a child is administered a fifth dose of the Polio vaccine at age 4 years - 4 days that the dose is valid.  No further doses should be forecast.  The series is complete."}],"gender":"female","birthDate":"2016-07-03"}},{"name":"immunization","resource":{"resourceType":"Immunization","id":"2013-0692-dose1","status":"completed","date":"2016-09-03T00:00:00.000","vaccineCode":{"coding":[{"system":"http://hl7.org/fhir/sid/cvx","code":"110","display":"PEDIARIX"},{"system":"http://hl7.org/fhir/v2/0227","code":"SKB","display":"PEDIARIX"}]},"patient":{"reference":"Patient/2013-0692"},"wasNotGiven":false,"reported":false}},{"name":"immunization","resource":{"resourceType":"Immunization","id":"2013-0692-dose2","status":"completed","date":"2016-10-03T00:00:00.000","vaccineCode":{"coding":[{"system":"http://hl7.org/fhir/sid/cvx","code":"110","display":"PEDIARIX"},{"system":"http://hl7.org/fhir/v2/0227","code":"SKB","display":"PEDIARIX"}]},"patient":{"reference":"Patient/2013-0692"},"wasNotGiven":false,"reported":false}},{"name":"immunization","resource":{"resourceType":"Immunization","id":"2013-0692-dose3","status":"completed","date":"2017-02-04T00:00:00.000","vaccineCode":{"coding":[{"system":"http://hl7.org/fhir/sid/cvx","code":"110","display":"PEDIARIX"},{"system":"http://hl7.org/fhir/v2/0227","code":"SKB","display":"PEDIARIX"}]},"patient":{"reference":"Patient/2013-0692"},"wasNotGiven":false,"reported":false}},{"name":"immunization","resource":{"resourceType":"Immunization","id":"2013-0692-dose4","status":"completed","date":"2017-10-12T00:00:00.000","vaccineCode":{"coding":[{"system":"http://hl7.org/fhir/sid/cvx","code":"110","display":"PEDIARIX"},{"system":"http://hl7.org/fhir/v2/0227","code":"SKB","display":"PEDIARIX"}]},"patient":{"reference":"Patient/2013-0692"},"wasNotGiven":false,"reported":false}},{"name":"immunization","resource":{"resourceType":"Immunization","id":"2013-0692-dose5","status":"completed","date":"2020-06-29T00:00:00.000","vaccineCode":{"coding":[{"system":"http://hl7.org/fhir/sid/cvx","code":"110","display":"PEDIARIX"},{"system":"http://hl7.org/fhir/v2/0227","code":"SKB","display":"PEDIARIX"}]},"patient":{"reference":"Patient/2013-0692"},"wasNotGiven":false,"reported":false}}]},"request":{"method":"PUT","url":"Parameters"}},{"resource":{"resourceType":"Parameters","parameter":[{"name":"recommendation","resource":{"resourceType":"ImmunizationRecommendation","patient":{"reference":"Patient/2013-0692"},"recommendation":[{"date":"2020-06-29T00:00:00.000","vaccineCode":{"coding":[{"system":"http://hl7.org/fhir/sid/cvx","display":"POL"}]},"forecastStatus":{"coding":[{"system":"http://hl7.org/fhir/us/ImmunizationFHIRDS/CodeSystem/ForecastStatus","code":"complete","display":"Complete"}]},"dateCriterion":[{"code":{"coding":[{"system":"http://loinc.org","code":"30981-5","display":"Earliest date to give"}]},"value":"2999-12-31T00:00:00.000"},{"code":{"coding":[{"system":"http://loinc.org","code":"30980-7","display":"Date vaccine due"}]},"value":"2999-12-31T00:00:00.000"},{"code":{"coding":[{"system":"http://loinc.org","code":"59778-1","display":"Date when overdue for immunization"}]},"value":"2999-12-31T00:00:00.000"}],"protocol":{"description":"Evaluation_Test_Type: Age: At Absolute Minimum\nForecast_Test_Type: EvaluationNot recommended: series complete\nGeneral_Description: This test case describes when a child is administered a fifth dose of the Polio vaccine at age 4 years - 4 days that the dose is valid.  No further doses should be forecast.  The series is complete.","series":"POL"}}]}}]},"request":{"method":"PUT","url":"Parameters"}}]}